src/__init__.py
src/__main__.py
src/connector.py
base_package_velsis-0.0.1.dist-info/METADATA
base_package_velsis-0.0.1.dist-info/WHEEL
base_package_velsis-0.0.1.dist-info/top_level.txt
base_package_velsis-0.0.1.dist-info/RECORD
