Metadata-Version: 2.1
Name: base-package-velsis
Version: 0.0.1
Summary: A base to create new packages
Home-page: UNKNOWN
Author: Maykon Schier
Author-email: maykonschier@gmail.com
License: UNKNOWN
Keywords: python,base
Platform: UNKNOWN
Classifier: Development Status :: 1 - Planning
Classifier: Intended Audience :: Education
Classifier: Programming Language :: Python :: 3 :: Only
Classifier: Operating System :: Unix
Classifier: License :: OSI Approved :: BSD License
Classifier: Operating System :: POSIX :: Linux
Requires-Dist: py-zabbix
Requires-Dist: requests
